AUTHORS.txt
LICENSE.txt
MANIFEST.in
README.rst
setup.py
lighttpdrecipe/__init__.py
lighttpdrecipe/buildoutjinja.py
lighttpdrecipe/djangorecipe_fcgi.jinja
lighttpdrecipe/recipe.py
lighttpdrecipe.egg-info/PKG-INFO
lighttpdrecipe.egg-info/SOURCES.txt
lighttpdrecipe.egg-info/dependency_links.txt
lighttpdrecipe.egg-info/entry_points.txt
lighttpdrecipe.egg-info/not-zip-safe
lighttpdrecipe.egg-info/requires.txt
lighttpdrecipe.egg-info/top_level.txt