Metadata-Version: 1.0
Name: lighttpdrecipe
Version: 0.2.5
Summary: Buildout recipe for generating Lighttpd configuration files
Home-page: http://github.com/redvasily/lighttpdrecipe/tree/master/
Author: Vasily Sulatskov
Author-email: redvasily@gmail.com
License: UNKNOWN
Download-URL: http://cloud.github.com/downloads/redvasily/lighttpdrecipe/
Platform: UNKNOWN
Classifier: Development Status :: 4 - Beta
Classifier: Environment :: Web Environment
Classifier: Framework :: Buildout
Classifier: Intended Audience :: Developers
Classifier: License :: OSI Approved :: BSD License
Classifier: Operating System :: OS Independent
Classifier: Programming Language :: Python
Classifier: Topic :: Software Development :: Libraries :: Python Modules
